FlavorTexts/FlavorTexts.py
FlavorTexts/__init__.py
FlavorTexts-0.1.0.dist-info/LICENSE
FlavorTexts-0.1.0.dist-info/METADATA
FlavorTexts-0.1.0.dist-info/WHEEL
FlavorTexts-0.1.0.dist-info/top_level.txt
FlavorTexts-0.1.0.dist-info/RECORD
