Metadata-Version: 2.1
Name: FlavorTexts
Version: 0.1.0
Summary: A pure-python recreation of Zack Freedman's FlavorText Arduino IDE Library
Home-page: https://github.com/A-c0rN/FlavorTexts
Author: A-c0rN
Author-email: acrn@gwes-eas.network
License: ODbL-1.0
Keywords: random text insane
Platform: UNKNOWN
Classifier: Development Status :: 5 - Production/Stable
Classifier: License :: Other/Proprietary License
Classifier: Programming Language :: Python
Classifier: Programming Language :: Python :: 3.6
Classifier: Programming Language :: Python :: 3.7
Classifier: Programming Language :: Python :: 3.8
Classifier: Programming Language :: Python :: 3.9
Classifier: Programming Language :: Python :: 3.10
Classifier: Intended Audience :: Developers
Classifier: Operating System :: OS Independent
Classifier: Topic :: Software Development :: Libraries
Classifier: Topic :: Utilities
License-File: LICENSE
Requires-Dist: FlavorTexts
